{
  "empresa": {
    "nombre": "Dev Costa Rica",
    "direccion": "Heredia, Costa Rica",
    "telefono": "2222-3344",
    "departamentos": [
      2,
      3,
      4
    ],
    "empleados": [
      1,
      2
    ]
  },
  "departamentos": [
    {
      "id": 2,
      "nombre": "Ventas",
      "empleados": [
        1
      ]
    },
    {
      "id": 3,
      "nombre": "Marketing",
      "empleados": []
    },
    {
      "id": 4,
      "nombre": "Tecnología",
      "empleados": [
        2
      ]
    }
  ],
  "empleados": [
    {
      "id": 1,
      "nombre": "Juan Perez",
      "puesto": "Contador",
      "departamentoId": 2
    },
    {
      "id": 2,
      "nombre": "Esteban Rojas",
      "puesto": "Desarrollador Backend",
      "departamentoId": 4
    }
  ]
}